food_trucks_boston/__init__.py
food_trucks_boston/test.py
food_trucks_boston-0.22.data/scripts/foodtrucks
food_trucks_boston-0.22.data/scripts/test.py
food_trucks_boston-0.22.dist-info/METADATA
food_trucks_boston-0.22.dist-info/RECORD
food_trucks_boston-0.22.dist-info/WHEEL
food_trucks_boston-0.22.dist-info/top_level.txt
