Metadata-Version: 2.1
Name: food-trucks-boston
Version: 0.22
Summary: Know where the food trucks are in Boston, from the command line.
Home-page: https://github.com/DennisMelamed/food_trucks_boston.git
Author: dennis.melamed
Author-email: dennis@dennismelamed.me
License: UNKNOWN
Platform: UNKNOWN
Requires-Dist: jsonpath-ng
Requires-Dist: click
Requires-Dist: esridump
Requires-Dist: fuzzywuzzy
Requires-Dist: numpy
Requires-Dist: prettytable
Requires-Dist: python-Levenshtein
